quick_python_project/__init__.py
quick_python_project/cli.py
quick_python_project/project_generation.py
quick_python_project/version.py
quick_python_project/templates/template_.gitignore
quick_python_project/templates/template_README.md
quick_python_project/templates/template___init__.py
quick_python_project/templates/template_main.py
quick_python_project/templates/template_pyproject.toml
quick_python_project-1.0.2.dist-info/LICENSE
quick_python_project-1.0.2.dist-info/METADATA
quick_python_project-1.0.2.dist-info/WHEEL
quick_python_project-1.0.2.dist-info/entry_points.txt
quick_python_project-1.0.2.dist-info/top_level.txt
quick_python_project-1.0.2.dist-info/RECORD
