Metadata-Version: 2.1
Name: quick_python_project
Version: 1.0.2
Summary: A CLI tool to create empty Python projects
Author-email: James Berkheimer <james.berkheimer@gmail.com>
License: MIT
Project-URL: homepage, https://github.com/james-berkheimer/quick_python_project
Platform: any
Classifier: Programming Language :: Python :: 3
Classifier: License :: OSI Approved :: MIT License
Classifier: Operating System :: OS Independent
Requires-Python: >=3.9
License-File: LICENSE
Requires-Dist: click
Requires-Dist: colorlog
Provides-Extra: dev
Requires-Dist: build; extra == "dev"
Requires-Dist: coverage; extra == "dev"
Requires-Dist: covdefaults; extra == "dev"
Requires-Dist: pytest; extra == "dev"
Requires-Dist: ruff; extra == "dev"
Requires-Dist: tox; extra == "dev"
Requires-Dist: twine; extra == "dev"
